fsb5/__init__.py
fsb5/ima.py
fsb5/pcm.py
fsb5/utils.py
fsb5/vorbis.py
fsb5/vorbis_headers.py
trimo_fsb5-0.1.1.dist-info/METADATA
trimo_fsb5-0.1.1.dist-info/WHEEL
trimo_fsb5-0.1.1.dist-info/entry_points.txt
trimo_fsb5-0.1.1.dist-info/licenses/LICENSE.md
trimo_fsb5-0.1.1.dist-info/RECORD
