Metadata-Version: 2.1
Name: TriMO-FSB5
Version: 0.1.1
Summary: 适用于 Python 的 FSB5 文件解析库及工具集。| Library and to extract audio from FSB5 (FMOD Sample Bank) files
Keywords: fsb5,fmod,audio
Author-Email: Simon Pinfold <simon@uint8.me>, =?utf-8?b?552/5LmQ57uE57uHIFRyaU1P?= <TriM-Organization@hotmail.com>
Maintainer-Email: =?utf-8?b?6YeR576/RWlsbGVz?= <EillesWan@outlook.com>
License: # Copyright Announcement
Classifier: Development Status :: 4 - Beta
Classifier: Intended Audience :: Developers
Classifier: Natural Language :: Chinese (Simplified)
Classifier: Operating System :: OS Independent
Classifier: Topic :: Software Development :: Libraries
Classifier: License :: OSI Approved :: Apache Software License
Classifier: Programming Language :: Python
Classifier: Programming Language :: Python :: 3
Classifier: Programming Language :: Python :: 3.6
Classifier: Programming Language :: Python :: 3.7
Classifier: Programming Language :: Python :: 3.8
Classifier: Topic :: Multimedia :: Sound/Audio
Classifier: Topic :: Multimedia :: Sound/Audio :: Conversion
Requires-Python: >=3.6
